{
  "name": "all",
  "title": "All indicators",
  "resources": [
    {
      "path": "2-2/data.csv",
      "name": "2-2",
      "profile": "tabular-data-resource",
      "scheme": "file",
      "format": "csv",
      "hashing": "md5",
      "encoding": "utf-8",
      "schema": {
        "fields": [
          {
            "name": "Year",
            "type": "integer",
            "title": "Jahr"
          },
          {
            "name": "Units",
            "type": "string",
            "constraints": {
              "enum": [
                "Prozent",
                ""
              ]
            },
            "title": "Units"
          },
          {
            "name": "Value",
            "type": "number",
            "title": "Value"
          }
        ]
      },
      "title": "Unterstützung guter Regierungsführung bei der Erreichung einer angemessenen Ernährung weltweit"
    },
    {
      "path": "14-1-a/data.csv",
      "name": "14-1-a",
      "profile": "tabular-data-resource",
      "scheme": "file",
      "format": "csv",
      "hashing": "md5",
      "encoding": "utf-8",
      "schema": {
        "fields": [
          {
            "name": "Year",
            "type": "integer",
            "title": "Jahr"
          },
          {
            "name": "Units",
            "type": "string",
            "constraints": {
              "enum": [
                "Milligramm pro Liter",
                ""
              ]
            },
            "title": "Units"
          },
          {
            "name": "time series",
            "type": "string",
            "constraints": {
              "enum": [
                "aa) Ostsee",
                "ab) Nordsee",
                ""
              ]
            },
            "title": "Zeitreihe"
          },
          {
            "name": "Value",
            "type": "number",
            "title": "Value"
          }
        ]
      },
      "title": "Nährstoffeinträge in Küsten- und Meeresgewässer - Stickstoffeintrag über die Zuflüsse in die Ost- und Nordsee"
    },
    {
      "path": "5-1-f/data.csv",
      "name": "5-1-f",
      "profile": "tabular-data-resource",
      "scheme": "file",
      "format": "csv",
      "hashing": "md5",
      "encoding": "utf-8",
      "schema": {
        "fields": [
          {
            "name": "Year",
            "type": "integer",
            "title": "Jahr"
          },
          {
            "name": "Units",
            "type": "string",
            "constraints": {
              "enum": [
                "1 000",
                ""
              ]
            },
            "title": "Units"
          },
          {
            "name": "Value",
            "type": "number",
            "title": "Value"
          }
        ]
      },
      "title": "Berufliche Qualifizierung von Frauen und Mädchen durch deutsche entwicklungspolitische Zusammenarbeit"
    },
    {
      "path": "16-3-ab/data.csv",
      "name": "16-3-ab",
      "profile": "tabular-data-resource",
      "scheme": "file",
      "format": "csv",
      "hashing": "md5",
      "encoding": "utf-8",
      "schema": {
        "fields": [
          {
            "name": "Year",
            "type": "integer",
            "title": "Jahr"
          },
          {
            "name": "Units",
            "type": "string",
            "constraints": {
              "enum": [
                "Anzahl",
                ""
              ]
            },
            "title": "Units"
          },
          {
            "name": "Series",
            "type": "string",
            "constraints": {
              "enum": [
                "a) Corruption Perceptions Index in Deutschland",
                "b) Anzahl der Partnerländern der deutschen Entwicklungszusammenarbeit mit verbessertem CPI",
                ""
              ]
            },
            "title": "Series"
          },
          {
            "name": "Value",
            "type": "number",
            "title": "Value"
          }
        ]
      },
      "title": "Corruption Perceptions Index in Deutschland sowie in den Partnerländern der deutschen Entwicklungszusammenarbeit"
    },
    {
      "path": "3-1-a/data.csv",
      "name": "3-1-a",
      "profile": "tabular-data-resource",
      "scheme": "file",
      "format": "csv",
      "hashing": "md5",
      "encoding": "utf-8",
      "schema": {
        "fields": [
          {
            "name": "Year",
            "type": "integer",
            "title": "Jahr"
          },
          {
            "name": "Units",
            "type": "string",
            "constraints": {
              "enum": [
                "Je 100 000 Einwohner/-innen",
                ""
              ]
            },
            "title": "Units"
          },
          {
            "name": "sex",
            "type": "string",
            "constraints": {
              "enum": [
                "Weiblich",
                "Männlich",
                ""
              ]
            },
            "title": "Geschlecht"
          },
          {
            "name": "type of treatment",
            "type": "string",
            "constraints": {
              "enum": [
                "Durch Prävention vermeidbare Sterblichkeit",
                "Durch Behandlung vermeidbare Sterblichkeit",
                ""
              ]
            },
            "title": "Art der Maßnahme"
          },
          {
            "name": "Value",
            "type": "number",
            "title": "Value"
          }
        ]
      },
      "title": "Durch Prävention und Behandlung vermeidbare Sterblichkeit"
    },
    {
      "path": "4-2-ab/data.csv",
      "name": "4-2-ab",
      "profile": "tabular-data-resource",
      "scheme": "file",
      "format": "csv",
      "hashing": "md5",
      "encoding": "utf-8",
      "schema": {
        "fields": [
          {
            "name": "Year",
            "type": "integer",
            "title": "Jahr"
          },
          {
            "name": "Units",
            "type": "string",
            "constraints": {
              "enum": [
                "Prozent",
                ""
              ]
            },
            "title": "Units"
          },
          {
            "name": "Series",
            "type": "string",
            "constraints": {
              "enum": [
                "a) 0- bis 2-Jährige",
                "b) 3- bis 5-Jährige",
                ""
              ]
            },
            "title": "Series"
          },
          {
            "name": "type of care",
            "type": "string",
            "constraints": {
              "enum": [
                "Kindertageseinrichtungen",
                "Kindertagespflege",
                ""
              ]
            },
            "title": "Art der Betreuung"
          },
          {
            "name": "Value",
            "type": "number",
            "title": "Value"
          }
        ]
      },
      "title": "Ganztagsbetreuung für Kinder"
    },
    {
      "path": "10-1/data.csv",
      "name": "10-1",
      "profile": "tabular-data-resource",
      "scheme": "file",
      "format": "csv",
      "hashing": "md5",
      "encoding": "utf-8",
      "schema": {
        "fields": [
          {
            "name": "Year",
            "type": "integer",
            "title": "Jahr"
          },
          {
            "name": "Units",
            "type": "string",
            "constraints": {
              "enum": [
                "Prozent",
                "Prozentpunkte",
                ""
              ]
            },
            "title": "Units"
          },
          {
            "name": "Series",
            "type": "string",
            "constraints": {
              "enum": [
                "Ausländer",
                "Deutsche",
                "Differenz",
                ""
              ]
            },
            "title": "Series"
          },
          {
            "name": "sex",
            "type": "string",
            "constraints": {
              "enum": [
                "Weiblich",
                "Männlich",
                ""
              ]
            },
            "title": "Geschlecht"
          },
          {
            "name": "Value",
            "type": "number",
            "title": "Value"
          }
        ]
      },
      "title": "Ausländische Schulabsolvierende"
    },
    {
      "path": "5-1-g/data.csv",
      "name": "5-1-g",
      "profile": "tabular-data-resource",
      "scheme": "file",
      "format": "csv",
      "hashing": "md5",
      "encoding": "utf-8",
      "schema": {
        "fields": [
          {
            "name": "Year",
            "type": "integer",
            "title": "Jahr"
          },
          {
            "name": "Units",
            "type": "string",
            "constraints": {
              "enum": [
                "Prozent",
                ""
              ]
            },
            "title": "Units"
          },
          {
            "name": "Value",
            "type": "number",
            "title": "Value"
          }
        ]
      },
      "title": "Anteil der Geschlechtergleichstellung berücksichtigenden Projektmittel in der deutschen Entwicklungszusammenarbeit"
    },
    {
      "path": "10-2/data.csv",
      "name": "10-2",
      "profile": "tabular-data-resource",
      "scheme": "file",
      "format": "csv",
      "hashing": "md5",
      "encoding": "utf-8",
      "schema": {
        "fields": [
          {
            "name": "Year",
            "type": "integer",
            "title": "Jahr"
          },
          {
            "name": "Units",
            "type": "string",
            "constraints": {
              "enum": [
                "Gini-Koeffizient",
                ""
              ]
            },
            "title": "Units"
          },
          {
            "name": "time series",
            "type": "string",
            "constraints": {
              "enum": [
                "<u>Zeitreihe des Indikators:</u> Gini-Koeffizient des verfügbaren Äquivalenzeinkommens",
                "<u>Zusätzliche Zeitreihe:</u> Gini-Koeffizient des verfügbaren Äquivalenzeinkommens vor Sozialleistungen",
                "<u>Zusätzliche Zeitreihe:</u> Gini-Koeffizient des Marktequivalenzeinkommens",
                "<u>Zusätzliche Zeitreihe:</u> Gini-Koeffizient des Vermögens",
                ""
              ]
            },
            "title": "Zeitreihe"
          },
          {
            "name": "area",
            "type": "string",
            "constraints": {
              "enum": [
                "Deutschland",
                "Europäische Union",
                "Eurozone",
                ""
              ]
            },
            "title": "Gebiet"
          },
          {
            "name": "Value",
            "type": "number",
            "title": "Value"
          }
        ]
      },
      "title": "Gini-Koeffizient des Einkommens nach Sozialtransfers"
    },
    {
      "path": "4-1-a/data.csv",
      "name": "4-1-a",
      "profile": "tabular-data-resource",
      "scheme": "file",
      "format": "csv",
      "hashing": "md5",
      "encoding": "utf-8",
      "schema": {
        "fields": [
          {
            "name": "Year",
            "type": "integer",
            "title": "Jahr"
          },
          {
            "name": "Units",
            "type": "string",
            "constraints": {
              "enum": [
                "Prozent",
                ""
              ]
            },
            "title": "Units"
          },
          {
            "name": "sex",
            "type": "string",
            "constraints": {
              "enum": [
                "Weiblich",
                "Männlich",
                ""
              ]
            },
            "title": "Geschlecht"
          },
          {
            "name": "Value",
            "type": "number",
            "title": "Value"
          }
        ]
      },
      "title": "Frühe Schul- und Ausbildungsabgängerinnen und -abgänger"
    },
    {
      "path": "7-2-b/data.csv",
      "name": "7-2-b",
      "profile": "tabular-data-resource",
      "scheme": "file",
      "format": "csv",
      "hashing": "md5",
      "encoding": "utf-8",
      "schema": {
        "fields": [
          {
            "name": "Year",
            "type": "integer",
            "title": "Jahr"
          },
          {
            "name": "Units",
            "type": "string",
            "constraints": {
              "enum": [
                "Prozent",
                ""
              ]
            },
            "title": "Units"
          },
          {
            "name": "Value",
            "type": "number",
            "title": "Value"
          }
        ]
      },
      "title": "Anteil des Stroms aus erneuerbaren Energiequellen am Bruttostromverbrauch"
    },
    {
      "path": "11-3-b/data.csv",
      "name": "11-3-b",
      "profile": "tabular-data-resource",
      "scheme": "file",
      "format": "csv",
      "hashing": "md5",
      "encoding": "utf-8",
      "schema": {
        "fields": [
          {
            "name": "Year",
            "type": "integer",
            "title": "Jahr"
          },
          {
            "name": "Units",
            "type": "string",
            "constraints": {
              "enum": [
                "Prozent",
                ""
              ]
            },
            "title": "Units"
          },
          {
            "name": "Value",
            "type": "number",
            "title": "Value"
          }
        ]
      },
      "title": "Erreichbarkeit von für die Erholung geeigneten Grünflächen in Städten"
    },
    {
      "path": "5-1-a/data.csv",
      "name": "5-1-a",
      "profile": "tabular-data-resource",
      "scheme": "file",
      "format": "csv",
      "hashing": "md5",
      "encoding": "utf-8",
      "schema": {
        "fields": [
          {
            "name": "Year",
            "type": "integer",
            "title": "Jahr"
          },
          {
            "name": "Units",
            "type": "string",
            "constraints": {
              "enum": [
                "Prozent",
                ""
              ]
            },
            "title": "Units"
          },
          {
            "name": "Series",
            "type": "string",
            "constraints": {
              "enum": [
                "<u>Zeitreihe des Indikators:</u> Unbereinigter Gender Pay Gap",
                "<u>Zusätzliche Zeitreihe:</u> Bereinigter Gender Pay Gap",
                ""
              ]
            },
            "title": "Series"
          },
          {
            "name": "Value",
            "type": "number",
            "title": "Value"
          }
        ]
      },
      "title": "Verdienstabstand zwischen Frauen und Männern"
    },
    {
      "path": "11-1-c/data.csv",
      "name": "11-1-c",
      "profile": "tabular-data-resource",
      "scheme": "file",
      "format": "csv",
      "hashing": "md5",
      "encoding": "utf-8",
      "schema": {
        "fields": [
          {
            "name": "Year",
            "type": "integer",
            "title": "Jahr"
          },
          {
            "name": "Units",
            "type": "string",
            "constraints": {
              "enum": [
                "2000 = 100",
                "Einwohner/-innen pro km² Siedlungs- und Verkehrsfläche",
                ""
              ]
            },
            "title": "Units"
          },
          {
            "name": "degree of urbanisation",
            "type": "string",
            "constraints": {
              "enum": [
                "Nicht-ländliche Gebiete",
                "Ländliche Gebiete",
                ""
              ]
            },
            "title": "Verstädterungsgrad"
          },
          {
            "name": "Value",
            "type": "number",
            "title": "Value"
          }
        ]
      },
      "title": "Siedlungsdichte"
    },
    {
      "path": "15-3/data.csv",
      "name": "15-3",
      "profile": "tabular-data-resource",
      "scheme": "file",
      "format": "csv",
      "hashing": "md5",
      "encoding": "utf-8",
      "schema": {
        "fields": [
          {
            "name": "Year",
            "type": "integer",
            "title": "Jahr"
          },
          {
            "name": "Units",
            "type": "string",
            "constraints": {
              "enum": [
                "Prozent",
                ""
              ]
            },
            "title": "Units"
          },
          {
            "name": "Value",
            "type": "number",
            "title": "Value"
          }
        ]
      },
      "title": "Bodenversiegelungsgrad"
    },
    {
      "path": "8-4/data.csv",
      "name": "8-4",
      "profile": "tabular-data-resource",
      "scheme": "file",
      "format": "csv",
      "hashing": "md5",
      "encoding": "utf-8",
      "schema": {
        "fields": [
          {
            "name": "Year",
            "type": "integer",
            "title": "Jahr"
          },
          {
            "name": "Units",
            "type": "string",
            "constraints": {
              "enum": [
                "1 000 Euro",
                ""
              ]
            },
            "title": "Units"
          },
          {
            "name": "Value",
            "type": "number",
            "title": "Value"
          }
        ]
      },
      "title": "Bruttoinlandsprodukt je Einwohnerin und Einwohner"
    },
    {
      "path": "9-1-a/data.csv",
      "name": "9-1-a",
      "profile": "tabular-data-resource",
      "scheme": "file",
      "format": "csv",
      "hashing": "md5",
      "encoding": "utf-8",
      "schema": {
        "fields": [
          {
            "name": "Year",
            "type": "integer",
            "title": "Jahr"
          },
          {
            "name": "Units",
            "type": "string",
            "constraints": {
              "enum": [
                "Prozent",
                ""
              ]
            },
            "title": "Units"
          },
          {
            "name": "sector",
            "type": "string",
            "constraints": {
              "enum": [
                "Staat und private Institutionen ohne Erwerbszweck",
                "Hochschulen",
                "Wirtschaft",
                ""
              ]
            },
            "title": "Sektor"
          },
          {
            "name": "Value",
            "type": "number",
            "title": "Value"
          }
        ]
      },
      "title": "Private und öffentliche Ausgaben für Forschung und Entwicklung"
    },
    {
      "path": "3-1-f/data.csv",
      "name": "3-1-f",
      "profile": "tabular-data-resource",
      "scheme": "file",
      "format": "csv",
      "hashing": "md5",
      "encoding": "utf-8",
      "schema": {
        "fields": [
          {
            "name": "Year",
            "type": "integer",
            "title": "Jahr"
          },
          {
            "name": "Units",
            "type": "string",
            "constraints": {
              "enum": [
                "Prozent",
                ""
              ]
            },
            "title": "Units"
          },
          {
            "name": "sex",
            "type": "string",
            "constraints": {
              "enum": [
                "Weiblich",
                "Männlich",
                ""
              ]
            },
            "title": "Geschlecht"
          },
          {
            "name": "age group",
            "type": "string",
            "constraints": {
              "enum": [
                "18 bis unter 20 Jahre",
                "20 bis unter 25 Jahre",
                "25 bis unter 30 Jahre",
                "30 bis unter 35 Jahre",
                "35 bis unter 40 Jahre",
                "40 bis unter 45 Jahre",
                "45 bis unter 50 Jahre",
                "50 bis unter 55 Jahre",
                "55 bis unter 60 Jahre",
                "60 bis unter 65 Jahre",
                "65 bis unter 70 Jahre",
                "70 bis unter 75 Jahre",
                "75 Jahre und älter",
                ""
              ]
            },
            "title": "Altersklasse"
          },
          {
            "name": "Value",
            "type": "number",
            "title": "Value"
          }
        ]
      },
      "title": "Adipositasquote von Erwachsenen"
    },
    {
      "path": "12-1-a/data.csv",
      "name": "12-1-a",
      "profile": "tabular-data-resource",
      "scheme": "file",
      "format": "csv",
      "hashing": "md5",
      "encoding": "utf-8",
      "schema": {
        "fields": [
          {
            "name": "Year",
            "type": "integer",
            "title": "Jahr"
          },
          {
            "name": "Units",
            "type": "string",
            "constraints": {
              "enum": [
                "Prozent",
                ""
              ]
            },
            "title": "Units"
          },
          {
            "name": "Value",
            "type": "number",
            "title": "Value"
          }
        ]
      },
      "title": "Marktanteil von Produkten mit staatlichen Nachhaltigkeitssiegeln"
    },
    {
      "path": "4-1-c/data.csv",
      "name": "4-1-c",
      "profile": "tabular-data-resource",
      "scheme": "file",
      "format": "csv",
      "hashing": "md5",
      "encoding": "utf-8",
      "schema": {
        "fields": [
          {
            "name": "Year",
            "type": "integer",
            "title": "Jahr"
          },
          {
            "name": "Units",
            "type": "string",
            "constraints": {
              "enum": [
                "Prozent",
                ""
              ]
            },
            "title": "Units"
          },
          {
            "name": "Value",
            "type": "number",
            "title": "Value"
          }
        ]
      },
      "title": "Schulen mit BNE-Label (Bildung für nachhaltige Entwicklung)"
    },
    {
      "path": "13-1-b/data.csv",
      "name": "13-1-b",
      "profile": "tabular-data-resource",
      "scheme": "file",
      "format": "csv",
      "hashing": "md5",
      "encoding": "utf-8",
      "schema": {
        "fields": [
          {
            "name": "Year",
            "type": "integer",
            "title": "Jahr"
          },
          {
            "name": "Units",
            "type": "string",
            "constraints": {
              "enum": [
                "Milliarden Euro",
                ""
              ]
            },
            "title": "Units"
          },
          {
            "name": "Value",
            "type": "number",
            "title": "Value"
          }
        ]
      },
      "title": "Internationale Klimafinanzierung zur Reduktion von Treibhausgasen und zur Anpassung an den Klimawandel"
    },
    {
      "path": "4-3-b/data.csv",
      "name": "4-3-b",
      "profile": "tabular-data-resource",
      "scheme": "file",
      "format": "csv",
      "hashing": "md5",
      "encoding": "utf-8",
      "schema": {
        "fields": [
          {
            "name": "Year",
            "type": "integer",
            "title": "Jahr"
          },
          {
            "name": "Units",
            "type": "string",
            "constraints": {
              "enum": [
                "Prozentpunkte",
                "Prozent",
                ""
              ]
            },
            "title": "Units"
          },
          {
            "name": "Series",
            "type": "string",
            "constraints": {
              "enum": [
                "Differenz zwischen <i>Keine Risikolage</i> und <i>Mindestens eine Risikolage</i>",
                "Nach Anzahl der Risikolagen",
                ""
              ]
            },
            "title": "Series"
          },
          {
            "name": "risk situation",
            "type": "string",
            "constraints": {
              "enum": [
                "Keine Risikolage",
                "Mindestens eine Risikolage",
                "Insgesamt",
                ""
              ]
            },
            "title": "Risikolage"
          },
          {
            "name": "Value",
            "type": "number",
            "title": "Value"
          }
        ]
      },
      "title": "Anteil der 17- und 18-Jährigen mit (angestrebter) Studienberechtigung"
    },
    {
      "path": "8-2-ab/data.csv",
      "name": "8-2-ab",
      "profile": "tabular-data-resource",
      "scheme": "file",
      "format": "csv",
      "hashing": "md5",
      "encoding": "utf-8",
      "schema": {
        "fields": [
          {
            "name": "Year",
            "type": "integer",
            "title": "Jahr"
          },
          {
            "name": "Units",
            "type": "string",
            "constraints": {
              "enum": [
                "Prozent",
                ""
              ]
            },
            "title": "Units"
          },
          {
            "name": "time series",
            "type": "string",
            "constraints": {
              "enum": [
                "a) Finanzierungssaldo",
                "b) Struktureller Finanzierungssaldo",
                "Bruttoinlandsprodukt (preisbereinigt)",
                ""
              ]
            },
            "title": "Zeitreihe"
          },
          {
            "name": "Value",
            "type": "number",
            "title": "Value"
          }
        ]
      },
      "title": "Staatsdefizit und strukturelles Defizit"
    },
    {
      "path": "11-2-c/data.csv",
      "name": "11-2-c",
      "profile": "tabular-data-resource",
      "scheme": "file",
      "format": "csv",
      "hashing": "md5",
      "encoding": "utf-8",
      "schema": {
        "fields": [
          {
            "name": "Year",
            "type": "integer",
            "title": "Jahr"
          },
          {
            "name": "Units",
            "type": "string",
            "constraints": {
              "enum": [
                "Minuten",
                ""
              ]
            },
            "title": "Units"
          },
          {
            "name": "time series",
            "type": "string",
            "constraints": {
              "enum": [
                "Bezogen auf die Mittel- und Oberzentren des jeweiligen Jahres",
                "Bezogen auf die Mittel- und Oberzentren des Jahres 2012",
                ""
              ]
            },
            "title": "Zeitreihe"
          },
          {
            "name": "Value",
            "type": "number",
            "title": "Value"
          }
        ]
      },
      "title": "Erreichbarkeit von Mittel- und Oberzentren mit öffentlichen Verkehrsmitteln"
    },
    {
      "path": "8-6/data.csv",
      "name": "8-6",
      "profile": "tabular-data-resource",
      "scheme": "file",
      "format": "csv",
      "hashing": "md5",
      "encoding": "utf-8",
      "schema": {
        "fields": [
          {
            "name": "Year",
            "type": "integer",
            "title": "Jahr"
          },
          {
            "name": "Units",
            "type": "string",
            "constraints": {
              "enum": [
                "Anzahl",
                ""
              ]
            },
            "title": "Units"
          },
          {
            "name": "Value",
            "type": "number",
            "title": "Value"
          }
        ]
      },
      "title": "Freiwillige Nachhaltigkeitsberichterstattung von Unternehmen nach dem Deutschen Nachhaltigkeitskodex (DNK)"
    },
    {
      "path": "17-3/data.csv",
      "name": "17-3",
      "profile": "tabular-data-resource",
      "scheme": "file",
      "format": "csv",
      "hashing": "md5",
      "encoding": "utf-8",
      "schema": {
        "fields": [
          {
            "name": "Year",
            "type": "integer",
            "title": "Jahr"
          },
          {
            "name": "Units",
            "type": "string",
            "constraints": {
              "enum": [
                "Prozent",
                ""
              ]
            },
            "title": "Units"
          },
          {
            "name": "time series",
            "type": "string",
            "constraints": {
              "enum": [
                "<u>Zeitreihe des Indikators:</u> Einfuhren",
                "<u>Zusätzliche Zeitreihe:</u> Einfuhren von weiterverarbeiteten Produkten",
                ""
              ]
            },
            "title": "Zeitreihe"
          },
          {
            "name": "Value",
            "type": "number",
            "title": "Value"
          }
        ]
      },
      "title": "Einfuhren aus am wenigsten entwickelten Ländern"
    },
    {
      "path": "16-4/data.csv",
      "name": "16-4",
      "profile": "tabular-data-resource",
      "scheme": "file",
      "format": "csv",
      "hashing": "md5",
      "encoding": "utf-8",
      "schema": {
        "fields": [
          {
            "name": "Year",
            "type": "integer",
            "title": "Jahr"
          },
          {
            "name": "Units",
            "type": "string",
            "constraints": {
              "enum": [
                "Anzahl der Bewertungen",
                ""
              ]
            },
            "title": "Units"
          },
          {
            "name": "Series",
            "type": "string",
            "constraints": {
              "enum": [
                "<u>Zeitreihe des Indikators:</u> Effectiveness",
                "<u>Zusätzliche Zeitreihe:</u> Technical Compliance",
                ""
              ]
            },
            "title": "Series"
          },
          {
            "name": "level of compliance",
            "type": "string",
            "constraints": {
              "enum": [
                "Solide oder hoch",
                "Gering oder moderat",
                "Größtenteils umgesetzt oder umgesetzt",
                "Nicht umgesetzt oder teilweise umgesetzt",
                ""
              ]
            },
            "title": "Grad der Umsetzung"
          },
          {
            "name": "Value",
            "type": "number",
            "title": "Value"
          }
        ]
      },
      "title": "Financial Action Task Force (FATF) rating effectiveness"
    },
    {
      "path": "8-1/data.csv",
      "name": "8-1",
      "profile": "tabular-data-resource",
      "scheme": "file",
      "format": "csv",
      "hashing": "md5",
      "encoding": "utf-8",
      "schema": {
        "fields": [
          {
            "name": "Year",
            "type": "integer",
            "title": "Jahr"
          },
          {
            "name": "Units",
            "type": "string",
            "constraints": {
              "enum": [
                "2010 = 100",
                ""
              ]
            },
            "title": "Units"
          },
          {
            "name": "time series",
            "type": "string",
            "constraints": {
              "enum": [
                "Gesamtrohstoffproduktivität",
                "Rohstoffeinsatz für Konsum, Investitionen und Exporte",
                "Wert von Konsum, Investitionen und Exporten (preisbereinigt)",
                "Rohstoffeinsatz für Konsum und Investitionen",
                "Rohstoffeinsatz für Exporte",
                ""
              ]
            },
            "title": "Zeitreihe"
          },
          {
            "name": "Value",
            "type": "number",
            "title": "Value"
          }
        ]
      },
      "title": "Gesamtrohstoffproduktivität"
    },
    {
      "path": "3-1-e/data.csv",
      "name": "3-1-e",
      "profile": "tabular-data-resource",
      "scheme": "file",
      "format": "csv",
      "hashing": "md5",
      "encoding": "utf-8",
      "schema": {
        "fields": [
          {
            "name": "Year",
            "type": "string",
            "title": "Jahr"
          },
          {
            "name": "Units",
            "type": "string",
            "constraints": {
              "enum": [
                "Prozent",
                ""
              ]
            },
            "title": "Units"
          },
          {
            "name": "time series",
            "type": "string",
            "constraints": {
              "enum": [
                "Übergewicht ohne Adipositas",
                "Adipositas",
                ""
              ]
            },
            "title": "Zeitreihe"
          },
          {
            "name": "sex",
            "type": "string",
            "constraints": {
              "enum": [
                "Weiblich",
                "Männlich",
                ""
              ]
            },
            "title": "Geschlecht"
          },
          {
            "name": "age group",
            "type": "string",
            "constraints": {
              "enum": [
                "3 bis unter 11 Jahre",
                "11 bis unter 18 Jahre",
                ""
              ]
            },
            "title": "Altersklasse"
          },
          {
            "name": "Value",
            "type": "number",
            "title": "Value"
          }
        ]
      },
      "title": "Adipositasquote von Kindern und Jugendlichen"
    },
    {
      "path": "11-2-a/data.csv",
      "name": "11-2-a",
      "profile": "tabular-data-resource",
      "scheme": "file",
      "format": "csv",
      "hashing": "md5",
      "encoding": "utf-8",
      "schema": {
        "fields": [
          {
            "name": "Year",
            "type": "integer",
            "title": "Jahr"
          },
          {
            "name": "Units",
            "type": "string",
            "constraints": {
              "enum": [
                "2015 = 100",
                ""
              ]
            },
            "title": "Units"
          },
          {
            "name": "time series",
            "type": "string",
            "constraints": {
              "enum": [
                "Endenergieverbrauch durch Güterbeförderung",
                "Güterbeförderungsleistung",
                "Energieverbrauch je Tonnenkilometer",
                ""
              ]
            },
            "title": "Zeitreihe"
          },
          {
            "name": "Value",
            "type": "number",
            "title": "Value"
          }
        ]
      },
      "title": "Endenergieverbrauch im Güterverkehr"
    },
    {
      "path": "2-1-b/data.csv",
      "name": "2-1-b",
      "profile": "tabular-data-resource",
      "scheme": "file",
      "format": "csv",
      "hashing": "md5",
      "encoding": "utf-8",
      "schema": {
        "fields": [
          {
            "name": "Year",
            "type": "integer",
            "title": "Jahr"
          },
          {
            "name": "Units",
            "type": "string",
            "constraints": {
              "enum": [
                "Prozent",
                ""
              ]
            },
            "title": "Units"
          },
          {
            "name": "Series",
            "type": "string",
            "constraints": {
              "enum": [
                "<u>Zeitreihe des Indikators:</u> Daten des Statistischen Bundesamtes",
                "<u>Zusätzliche Zeitreihe:</u> Daten des BMLEH",
                ""
              ]
            },
            "title": "Series"
          },
          {
            "name": "Value",
            "type": "number",
            "title": "Value"
          }
        ]
      },
      "title": "Ökologischer Landbau"
    },
    {
      "path": "8-5-c/data.csv",
      "name": "8-5-c",
      "profile": "tabular-data-resource",
      "scheme": "file",
      "format": "csv",
      "hashing": "md5",
      "encoding": "utf-8",
      "schema": {
        "fields": [
          {
            "name": "Year",
            "type": "integer",
            "title": "Jahr"
          },
          {
            "name": "Units",
            "type": "string",
            "constraints": {
              "enum": [
                "Prozent",
                ""
              ]
            },
            "title": "Units"
          },
          {
            "name": "type of collective bargaining agreement",
            "type": "string",
            "constraints": {
              "enum": [
                "Branchen-/Flächentarifvertrag",
                "Firmen-/Haustarifvertrag",
                ""
              ]
            },
            "title": "Art des Tarifvertrags"
          },
          {
            "name": "Value",
            "type": "number",
            "title": "Value"
          }
        ]
      },
      "title": "Tarifgebundene Beschäftigungsverhältnisse"
    },
    {
      "path": "8-5-ab/data.csv",
      "name": "8-5-ab",
      "profile": "tabular-data-resource",
      "scheme": "file",
      "format": "csv",
      "hashing": "md5",
      "encoding": "utf-8",
      "schema": {
        "fields": [
          {
            "name": "Year",
            "type": "integer",
            "title": "Jahr"
          },
          {
            "name": "Units",
            "type": "string",
            "constraints": {
              "enum": [
                "Prozent",
                ""
              ]
            },
            "title": "Units"
          },
          {
            "name": "Series",
            "type": "string",
            "constraints": {
              "enum": [
                "a) Insgesamt (20- bis 64-Jährige)",
                "b) Ältere (55- bis 64-Jährige)",
                ""
              ]
            },
            "title": "Series"
          },
          {
            "name": "sex",
            "type": "string",
            "constraints": {
              "enum": [
                "Weiblich",
                "Männlich",
                ""
              ]
            },
            "title": "Geschlecht"
          },
          {
            "name": "Value",
            "type": "number",
            "title": "Value"
          }
        ]
      },
      "title": "Erwerbstätigenquote"
    },
    {
      "path": "3-2-a/data.csv",
      "name": "3-2-a",
      "profile": "tabular-data-resource",
      "scheme": "file",
      "format": "csv",
      "hashing": "md5",
      "encoding": "utf-8",
      "schema": {
        "fields": [
          {
            "name": "Year",
            "type": "integer",
            "title": "Jahr"
          },
          {
            "name": "Units",
            "type": "string",
            "constraints": {
              "enum": [
                "2005 = 100",
                ""
              ]
            },
            "title": "Units"
          },
          {
            "name": "air pollutant",
            "type": "string",
            "constraints": {
              "enum": [
                "Insgesamt",
                "SO₂",
                "NOₓ",
                "NH₃",
                "NMVOC",
                "PM₂.₅",
                ""
              ]
            },
            "title": "Luftschadstoff"
          },
          {
            "name": "Value",
            "type": "number",
            "title": "Value"
          }
        ]
      },
      "title": "Emissionen von Luftschadstoffen"
    },
    {
      "path": "12-1-b/data.csv",
      "name": "12-1-b",
      "profile": "tabular-data-resource",
      "scheme": "file",
      "format": "csv",
      "hashing": "md5",
      "encoding": "utf-8",
      "schema": {
        "fields": [
          {
            "name": "Year",
            "type": "integer",
            "title": "Jahr"
          },
          {
            "name": "Units",
            "type": "string",
            "constraints": {
              "enum": [
                "2010 = 100",
                ""
              ]
            },
            "title": "Units"
          },
          {
            "name": "time series",
            "type": "string",
            "constraints": {
              "enum": [
                "ba) Direkter und indirekter Rohstoffeinsatz",
                "bb) Direkter und indirekter Energieverbrauch",
                "bc) Direkte und indirekte CO₂-Emissionen",
                ""
              ]
            },
            "title": "Zeitreihe"
          },
          {
            "name": "Value",
            "type": "number",
            "title": "Value"
          }
        ]
      },
      "title": "Globale Umweltinanspruchnahme durch den Konsum privater Haushalte"
    },
    {
      "path": "14-1-b/data.csv",
      "name": "14-1-b",
      "profile": "tabular-data-resource",
      "scheme": "file",
      "format": "csv",
      "hashing": "md5",
      "encoding": "utf-8",
      "schema": {
        "fields": [
          {
            "name": "Year",
            "type": "integer",
            "title": "Jahr"
          },
          {
            "name": "Units",
            "type": "string",
            "constraints": {
              "enum": [
                "Prozent",
                ""
              ]
            },
            "title": "Units"
          },
          {
            "name": "time series",
            "type": "string",
            "constraints": {
              "enum": [
                "Nachhaltig bewirtschaftete Fischbestände an allen MSY-untersuchten Beständen",
                "MSY-untersuchte Fischbestände an allen bewirtschafteten Beständen",
                ""
              ]
            },
            "title": "Zeitreihe"
          },
          {
            "name": "sea",
            "type": "string",
            "constraints": {
              "enum": [
                "Nordsee",
                "Ostsee",
                ""
              ]
            },
            "title": "Meer"
          },
          {
            "name": "Value",
            "type": "number",
            "title": "Value"
          }
        ]
      },
      "title": "Anteil der nachhaltig befischten Fischbestände in Nord- und Ostsee"
    },
    {
      "path": "12-4/data.csv",
      "name": "12-4",
      "profile": "tabular-data-resource",
      "scheme": "file",
      "format": "csv",
      "hashing": "md5",
      "encoding": "utf-8",
      "schema": {
        "fields": [
          {
            "name": "Year",
            "type": "integer",
            "title": "Jahr"
          },
          {
            "name": "Units",
            "type": "string",
            "constraints": {
              "enum": [
                "Prozent",
                ""
              ]
            },
            "title": "Units"
          },
          {
            "name": "Value",
            "type": "number",
            "title": "Value"
          }
        ]
      },
      "title": "Verbraucherverschuldung"
    },
    {
      "path": "7-1-ab/data.csv",
      "name": "7-1-ab",
      "profile": "tabular-data-resource",
      "scheme": "file",
      "format": "csv",
      "hashing": "md5",
      "encoding": "utf-8",
      "schema": {
        "fields": [
          {
            "name": "Year",
            "type": "integer",
            "title": "Jahr"
          },
          {
            "name": "Units",
            "type": "string",
            "constraints": {
              "enum": [
                "2008 = 100",
                ""
              ]
            },
            "title": "Units"
          },
          {
            "name": "Series",
            "type": "string",
            "constraints": {
              "enum": [
                "a) Endenergieproduktivität",
                "b) Primärenergieverbrauch",
                ""
              ]
            },
            "title": "Series"
          },
          {
            "name": "Value",
            "type": "number",
            "title": "Value"
          }
        ]
      },
      "title": "Endenergieproduktivität und Primärenergieverbrauch"
    },
    {
      "path": "3-2-b/data.csv",
      "name": "3-2-b",
      "profile": "tabular-data-resource",
      "scheme": "file",
      "format": "csv",
      "hashing": "md5",
      "encoding": "utf-8",
      "schema": {
        "fields": [
          {
            "name": "Year",
            "type": "integer",
            "title": "Jahr"
          },
          {
            "name": "Units",
            "type": "string",
            "constraints": {
              "enum": [
                "Prozent",
                ""
              ]
            },
            "title": "Units"
          },
          {
            "name": "Value",
            "type": "number",
            "title": "Value"
          }
        ]
      },
      "title": "Anteil der Bevölkerung mit erhöhter PM₂,₅-Feinstaubexposition"
    },
    {
      "path": "3-1-cd/data.csv",
      "name": "3-1-cd",
      "profile": "tabular-data-resource",
      "scheme": "file",
      "format": "csv",
      "hashing": "md5",
      "encoding": "utf-8",
      "schema": {
        "fields": [
          {
            "name": "Year",
            "type": "integer",
            "title": "Jahr"
          },
          {
            "name": "Units",
            "type": "string",
            "constraints": {
              "enum": [
                "Prozent",
                ""
              ]
            },
            "title": "Units"
          },
          {
            "name": "time series",
            "type": "string",
            "constraints": {
              "enum": [
                "c) Jugendliche",
                "d) Erwachsene",
                ""
              ]
            },
            "title": "Zeitreihe"
          },
          {
            "name": "sex",
            "type": "string",
            "constraints": {
              "enum": [
                "Weiblich",
                "Männlich",
                ""
              ]
            },
            "title": "Geschlecht"
          },
          {
            "name": "Value",
            "type": "number",
            "title": "Value"
          }
        ]
      },
      "title": "Raucherquote von Jugendlichen und Erwachsenen"
    },
    {
      "path": "15-4/data.csv",
      "name": "15-4",
      "profile": "tabular-data-resource",
      "scheme": "file",
      "format": "csv",
      "hashing": "md5",
      "encoding": "utf-8",
      "schema": {
        "fields": [
          {
            "name": "Year",
            "type": "integer",
            "title": "Jahr"
          },
          {
            "name": "Units",
            "type": "string",
            "constraints": {
              "enum": [
                "Millionen Hektar",
                ""
              ]
            },
            "title": "Units"
          },
          {
            "name": "sector",
            "type": "string",
            "constraints": {
              "enum": [
                "Nachhaltige bewirtschaftete Fläche",
                "Waldfläche nachhaltige Bewirtschaftung und Wiederherstellung",
                "Terrestrische Schutzgebiete und Mangrovenwälder in marinen Schutzgebieten",
                ""
              ]
            },
            "title": "Sektor"
          },
          {
            "name": "Value",
            "type": "number",
            "title": "Value"
          }
        ]
      },
      "title": "Bilaterale Beiträge der deutschen internationalen Kooperation zum Schutz, nachhaltiger Nutzung und Wiederherstellung von Land (inkl. Wald)"
    },
    {
      "path": "12-2-a/data.csv",
      "name": "12-2-a",
      "profile": "tabular-data-resource",
      "scheme": "file",
      "format": "csv",
      "hashing": "md5",
      "encoding": "utf-8",
      "schema": {
        "fields": [
          {
            "name": "Year",
            "type": "integer",
            "title": "Jahr"
          },
          {
            "name": "Units",
            "type": "string",
            "constraints": {
              "enum": [
                "Anzahl",
                "1 000",
                ""
              ]
            },
            "title": "Units"
          },
          {
            "name": "Series",
            "type": "string",
            "constraints": {
              "enum": [
                "<u>Zeitreihe des Indikators:</u> EMAS-Standorte",
                "<u>Zusätzliche Zeitreihe:</u> Beschäftigte in EMAS-Organisationen",
                "<u>Zusätzliche Zeitreihe:</u> EMAS-Organisationen",
                ""
              ]
            },
            "title": "Series"
          },
          {
            "name": "Value",
            "type": "number",
            "title": "Value"
          }
        ]
      },
      "title": "Umweltmanagementsystem (EMAS)"
    },
    {
      "path": "6-1-a/data.csv",
      "name": "6-1-a",
      "profile": "tabular-data-resource",
      "scheme": "file",
      "format": "csv",
      "hashing": "md5",
      "encoding": "utf-8",
      "schema": {
        "fields": [
          {
            "name": "Year",
            "type": "integer",
            "title": "Jahr"
          },
          {
            "name": "Units",
            "type": "string",
            "constraints": {
              "enum": [
                "Prozent",
                ""
              ]
            },
            "title": "Units"
          },
          {
            "name": "Value",
            "type": "number",
            "title": "Value"
          }
        ]
      },
      "title": "Phosphor in Fließgewässern"
    },
    {
      "path": "4-1-b/data.csv",
      "name": "4-1-b",
      "profile": "tabular-data-resource",
      "scheme": "file",
      "format": "csv",
      "hashing": "md5",
      "encoding": "utf-8",
      "schema": {
        "fields": [
          {
            "name": "Year",
            "type": "integer",
            "title": "Jahr"
          },
          {
            "name": "Units",
            "type": "string",
            "constraints": {
              "enum": [
                "Prozent",
                ""
              ]
            },
            "title": "Units"
          },
          {
            "name": "time series",
            "type": "string",
            "constraints": {
              "enum": [
                "<u>Zeitreihe des Indikators:</u> Akademisch Qualifizierte und beruflich Höherqualifizierte",
                "<u>Zusätzliche Zeitreihe:</u> Fachkräftepotenzial (insgesamt)",
                ""
              ]
            },
            "title": "Zeitreihe"
          },
          {
            "name": "qualification",
            "type": "string",
            "constraints": {
              "enum": [
                "Zweitausbildung, Ausbildung nach Abitur",
                "Höherqualifizierende Berufsausbildung",
                "Hochschulabschluss",
                "Erstausbildung",
                ""
              ]
            },
            "title": "Qualifizierung"
          },
          {
            "name": "sex",
            "type": "string",
            "constraints": {
              "enum": [
                "Weiblich",
                "Männlich",
                ""
              ]
            },
            "title": "Geschlecht"
          },
          {
            "name": "Value",
            "type": "number",
            "title": "Value"
          }
        ]
      },
      "title": "Akademisch Qualifizierte und beruflich Höherqualifizierte"
    },
    {
      "path": "2-1-a/data.csv",
      "name": "2-1-a",
      "profile": "tabular-data-resource",
      "scheme": "file",
      "format": "csv",
      "hashing": "md5",
      "encoding": "utf-8",
      "schema": {
        "fields": [
          {
            "name": "Year",
            "type": "integer",
            "title": "Jahr"
          },
          {
            "name": "Units",
            "type": "string",
            "constraints": {
              "enum": [
                "Kilogramm pro Hektar",
                ""
              ]
            },
            "title": "Units"
          },
          {
            "name": "time series",
            "type": "string",
            "constraints": {
              "enum": [
                "Gleitender Fünfjahresdurchschnitt bezogen auf das Endjahr",
                "Berechnete jährliche Werte",
                ""
              ]
            },
            "title": "Zeitreihe"
          },
          {
            "name": "Value",
            "type": "number",
            "title": "Value"
          }
        ]
      },
      "title": "Stickstoffüberschuss der Landwirtschaft"
    },
    {
      "path": "8-3/data.csv",
      "name": "8-3",
      "profile": "tabular-data-resource",
      "scheme": "file",
      "format": "csv",
      "hashing": "md5",
      "encoding": "utf-8",
      "schema": {
        "fields": [
          {
            "name": "Year",
            "type": "integer",
            "title": "Jahr"
          },
          {
            "name": "Units",
            "type": "string",
            "constraints": {
              "enum": [
                "Prozent",
                ""
              ]
            },
            "title": "Units"
          },
          {
            "name": "Value",
            "type": "number",
            "title": "Value"
          }
        ]
      },
      "title": "Verhältnis der Bruttoanlageinvestitionen zum Bruttoinlandsprodukt (Investitionsquote)"
    },
    {
      "path": "16-2/data.csv",
      "name": "16-2",
      "profile": "tabular-data-resource",
      "scheme": "file",
      "format": "csv",
      "hashing": "md5",
      "encoding": "utf-8",
      "schema": {
        "fields": [
          {
            "name": "Year",
            "type": "integer",
            "title": "Jahr"
          },
          {
            "name": "Units",
            "type": "string",
            "constraints": {
              "enum": [
                "Anzahl",
                ""
              ]
            },
            "title": "Units"
          },
          {
            "name": "display",
            "type": "string",
            "constraints": {
              "enum": [
                "Ausgebildetes Personal",
                "Noch fehlende Ausbildungsleistung",
                ""
              ]
            },
            "title": "Anzeigen"
          },
          {
            "name": "sex",
            "type": "string",
            "constraints": {
              "enum": [
                "Weiblich",
                "Männlich",
                ""
              ]
            },
            "title": "Geschlecht"
          },
          {
            "name": "Value",
            "type": "number",
            "title": "Value"
          }
        ]
      },
      "title": "Von der Bundeswehr ausgebildetes Personal zur Stärkung der Kleinwaffenkontrolle und Munitionssicherheit"
    },
    {
      "path": "15-1/data.csv",
      "name": "15-1",
      "profile": "tabular-data-resource",
      "scheme": "file",
      "format": "csv",
      "hashing": "md5",
      "encoding": "utf-8",
      "schema": {
        "fields": [
          {
            "name": "Year",
            "type": "integer",
            "title": "Jahr"
          },
          {
            "name": "Units",
            "type": "string",
            "constraints": {
              "enum": [
                "2030 = 100",
                ""
              ]
            },
            "title": "Units"
          },
          {
            "name": "time series",
            "type": "string",
            "constraints": {
              "enum": [
                "<u>Zeitreihe des Indikators:</u> Gesamtindikator",
                "Teilindikator Wälder",
                "Teilindikator Siedlungen",
                "Teilindikator Agrarland",
                "Teilindex Binnengewässer",
                "<u>Zusätzliche Zeitreihe:</u> Küsten/Meere",
                ""
              ]
            },
            "title": "Zeitreihe"
          },
          {
            "name": "Value",
            "type": "number",
            "title": "Value"
          }
        ]
      },
      "title": "Artenvielfalt und Landschaftsqualität"
    },
    {
      "path": "12-2-b/data.csv",
      "name": "12-2-b",
      "profile": "tabular-data-resource",
      "scheme": "file",
      "format": "csv",
      "hashing": "md5",
      "encoding": "utf-8",
      "schema": {
        "fields": [
          {
            "name": "Year",
            "type": "string",
            "title": "Jahr"
          },
          {
            "name": "Units",
            "type": "string",
            "constraints": {
              "enum": [
                "Anzahl",
                ""
              ]
            },
            "title": "Units"
          },
          {
            "name": "Series",
            "type": "string",
            "constraints": {
              "enum": [
                "<u>Zeitreihe des Indikators:</u> Nachhaltigkeitszertifizierte Kultur- und Medieneinrichtungen",
                "<u>Zusätzliche Zeitreihe:</u> Produktionen audiovisueller Medien, bei denen ökologische Standards eingehalten wurden",
                ""
              ]
            },
            "title": "Series"
          },
          {
            "name": "Value",
            "type": "number",
            "title": "Value"
          }
        ]
      },
      "title": "Nachhaltigkeitszertifizierte Kultur- und Medieneinrichtungen"
    },
    {
      "path": "4-3-a/data.csv",
      "name": "4-3-a",
      "profile": "tabular-data-resource",
      "scheme": "file",
      "format": "csv",
      "hashing": "md5",
      "encoding": "utf-8",
      "schema": {
        "fields": [
          {
            "name": "Year",
            "type": "integer",
            "title": "Jahr"
          },
          {
            "name": "Units",
            "type": "string",
            "constraints": {
              "enum": [
                "Prozent",
                ""
              ]
            },
            "title": "Units"
          },
          {
            "name": "sex",
            "type": "string",
            "constraints": {
              "enum": [
                "Weiblich",
                "Männlich",
                ""
              ]
            },
            "title": "Geschlecht"
          },
          {
            "name": "Value",
            "type": "number",
            "title": "Value"
          }
        ]
      },
      "title": "Weiterbildungsbeteiligung"
    },
    {
      "path": "3-3/data.csv",
      "name": "3-3",
      "profile": "tabular-data-resource",
      "scheme": "file",
      "format": "csv",
      "hashing": "md5",
      "encoding": "utf-8",
      "schema": {
        "fields": [
          {
            "name": "Year",
            "type": "integer",
            "title": "Jahr"
          },
          {
            "name": "Units",
            "type": "string",
            "constraints": {
              "enum": [
                "Millionen Euro",
                ""
              ]
            },
            "title": "Units"
          },
          {
            "name": "time series",
            "type": "string",
            "constraints": {
              "enum": [
                "Pandemieprävention und -reaktion",
                "Eindämmung der COVID-19-Pandemie",
                ""
              ]
            },
            "title": "Zeitreihe"
          },
          {
            "name": "Value",
            "type": "number",
            "title": "Value"
          }
        ]
      },
      "title": "Anteil der Länder, die Deutschland bei der Pandemieprävention, -vorsorge und -reaktion (PPR) unterstützt und die im Global Health Security Index (GHSI) Fortschritte gemacht haben, an der Anzahl der Länder, die Deutschland im Bereich PPR unterstützt"
    },
    {
      "path": "17-2/data.csv",
      "name": "17-2",
      "profile": "tabular-data-resource",
      "scheme": "file",
      "format": "csv",
      "hashing": "md5",
      "encoding": "utf-8",
      "schema": {
        "fields": [
          {
            "name": "Year",
            "type": "integer",
            "title": "Jahr"
          },
          {
            "name": "Units",
            "type": "string",
            "constraints": {
              "enum": [
                "Anzahl",
                ""
              ]
            },
            "title": "Units"
          },
          {
            "name": "time series",
            "type": "string",
            "constraints": {
              "enum": [
                "Studierende aus LDCs",
                "Studierende aus den übrigen Entwicklungs- und Schwellenländern",
                "Forschende aus LDCs",
                "Forschende aus den übrigen Entwicklungs- und Schwellenländern",
                ""
              ]
            },
            "title": "Zeitreihe"
          },
          {
            "name": "Value",
            "type": "number",
            "title": "Value"
          }
        ]
      },
      "title": "Studierende und Forschende aus Entwicklungsländern sowie aus am wenigsten entwickelten Ländern"
    },
    {
      "path": "11-2-b/data.csv",
      "name": "11-2-b",
      "profile": "tabular-data-resource",
      "scheme": "file",
      "format": "csv",
      "hashing": "md5",
      "encoding": "utf-8",
      "schema": {
        "fields": [
          {
            "name": "Year",
            "type": "integer",
            "title": "Jahr"
          },
          {
            "name": "Units",
            "type": "string",
            "constraints": {
              "enum": [
                "2015 = 100",
                ""
              ]
            },
            "title": "Units"
          },
          {
            "name": "time series",
            "type": "string",
            "constraints": {
              "enum": [
                "Endenergieverbrauch im Personenverkehr",
                "Personenbeförderungsleistung",
                "Energieverbrauch je Personenkilometer",
                ""
              ]
            },
            "title": "Zeitreihe"
          },
          {
            "name": "Value",
            "type": "number",
            "title": "Value"
          }
        ]
      },
      "title": "Endenergieverbrauch im Personenverkehr"
    },
    {
      "path": "17-1/data.csv",
      "name": "17-1",
      "profile": "tabular-data-resource",
      "scheme": "file",
      "format": "csv",
      "hashing": "md5",
      "encoding": "utf-8",
      "schema": {
        "fields": [
          {
            "name": "Year",
            "type": "integer",
            "title": "Jahr"
          },
          {
            "name": "Units",
            "type": "string",
            "constraints": {
              "enum": [
                "Prozent",
                ""
              ]
            },
            "title": "Units"
          },
          {
            "name": "Value",
            "type": "number",
            "title": "Value"
          }
        ]
      },
      "title": "Anteil öffentlicher Entwicklungsausgaben am Bruttonationaleinkommen"
    },
    {
      "path": "5-1-e/data.csv",
      "name": "5-1-e",
      "profile": "tabular-data-resource",
      "scheme": "file",
      "format": "csv",
      "hashing": "md5",
      "encoding": "utf-8",
      "schema": {
        "fields": [
          {
            "name": "Year",
            "type": "integer",
            "title": "Jahr"
          },
          {
            "name": "Units",
            "type": "string",
            "constraints": {
              "enum": [
                "Stunden",
                ""
              ]
            },
            "title": "Units"
          },
          {
            "name": "time series",
            "type": "string",
            "constraints": {
              "enum": [
                "Mütter",
                "Väter",
                "Differenz",
                ""
              ]
            },
            "title": "Zeitreihe"
          },
          {
            "name": "Value",
            "type": "number",
            "title": "Value"
          }
        ]
      },
      "title": "Durchschnittliche wöchentliche Erwerbsarbeitszeit bezogen auf alle Mütter und Väter"
    },
    {
      "path": "13-1-a/data.csv",
      "name": "13-1-a",
      "profile": "tabular-data-resource",
      "scheme": "file",
      "format": "csv",
      "hashing": "md5",
      "encoding": "utf-8",
      "schema": {
        "fields": [
          {
            "name": "Year",
            "type": "integer",
            "title": "Jahr"
          },
          {
            "name": "Units",
            "type": "string",
            "constraints": {
              "enum": [
                "1990 = 100",
                ""
              ]
            },
            "title": "Units"
          },
          {
            "name": "Value",
            "type": "number",
            "title": "Value"
          }
        ]
      },
      "title": "Treibhausgasemissionen"
    },
    {
      "path": "9-1-b/data.csv",
      "name": "9-1-b",
      "profile": "tabular-data-resource",
      "scheme": "file",
      "format": "csv",
      "hashing": "md5",
      "encoding": "utf-8",
      "schema": {
        "fields": [
          {
            "name": "Year",
            "type": "string",
            "title": "Jahr"
          },
          {
            "name": "Units",
            "type": "string",
            "constraints": {
              "enum": [
                "Prozent",
                ""
              ]
            },
            "title": "Units"
          },
          {
            "name": "time series",
            "type": "string",
            "constraints": {
              "enum": [
                "Alle leitungsgebundenen Technologien",
                "Reine Glasfasernetze (FTTB/H)",
                "Hybrid Fiber Coax (HFC)",
                ""
              ]
            },
            "title": "Zeitreihe"
          },
          {
            "name": "Value",
            "type": "number",
            "title": "Value"
          }
        ]
      },
      "title": "Breitbandausbau - Anteil der Haushalte mit Zugang zu Gigabit-Breitbandversorgung"
    },
    {
      "path": "11-1-a/data.csv",
      "name": "11-1-a",
      "profile": "tabular-data-resource",
      "scheme": "file",
      "format": "csv",
      "hashing": "md5",
      "encoding": "utf-8",
      "schema": {
        "fields": [
          {
            "name": "Year",
            "type": "integer",
            "title": "Jahr"
          },
          {
            "name": "Units",
            "type": "string",
            "constraints": {
              "enum": [
                "Hektar pro Tag",
                ""
              ]
            },
            "title": "Units"
          },
          {
            "name": "time series",
            "type": "string",
            "constraints": {
              "enum": [
                "Gleitender Vierjahresdurchschnitt",
                "Berechnete jährliche Werte",
                ""
              ]
            },
            "title": "Zeitreihe"
          },
          {
            "name": "type of area",
            "type": "string",
            "constraints": {
              "enum": [
                "Verkehrsfläche",
                "Erholungsfläche, Friedhof",
                "Siedlungsfläche (bebaut)",
                ""
              ]
            },
            "title": "Art der Fläche"
          },
          {
            "name": "Value",
            "type": "number",
            "title": "Value"
          }
        ]
      },
      "title": "Anstieg der Siedlungs- und Verkehrsfläche"
    },
    {
      "path": "7-2-a/data.csv",
      "name": "7-2-a",
      "profile": "tabular-data-resource",
      "scheme": "file",
      "format": "csv",
      "hashing": "md5",
      "encoding": "utf-8",
      "schema": {
        "fields": [
          {
            "name": "Year",
            "type": "integer",
            "title": "Jahr"
          },
          {
            "name": "Units",
            "type": "string",
            "constraints": {
              "enum": [
                "Prozent",
                ""
              ]
            },
            "title": "Units"
          },
          {
            "name": "Value",
            "type": "number",
            "title": "Value"
          }
        ]
      },
      "title": "Anteil erneuerbarer Energien am Bruttoendenergieverbrauch"
    },
    {
      "path": "15-2/data.csv",
      "name": "15-2",
      "profile": "tabular-data-resource",
      "scheme": "file",
      "format": "csv",
      "hashing": "md5",
      "encoding": "utf-8",
      "schema": {
        "fields": [
          {
            "name": "Year",
            "type": "integer",
            "title": "Jahr"
          },
          {
            "name": "Units",
            "type": "string",
            "constraints": {
              "enum": [
                "Prozent",
                ""
              ]
            },
            "title": "Units"
          },
          {
            "name": "Value",
            "type": "number",
            "title": "Value"
          }
        ]
      },
      "title": "Eutrophierung der Ökosysteme"
    },
    {
      "path": "5-1-bc/data.csv",
      "name": "5-1-bc",
      "profile": "tabular-data-resource",
      "scheme": "file",
      "format": "csv",
      "hashing": "md5",
      "encoding": "utf-8",
      "schema": {
        "fields": [
          {
            "name": "Year",
            "type": "integer",
            "title": "Jahr"
          },
          {
            "name": "Units",
            "type": "string",
            "constraints": {
              "enum": [
                "Prozent",
                ""
              ]
            },
            "title": "Units"
          },
          {
            "name": "time series",
            "type": "string",
            "constraints": {
              "enum": [
                "b) In Aufsichtsräten der börsennotierten und paritätisch mitbestimmten Unternehmen",
                "c) Im öffentlichen Dienst des Bundes",
                ""
              ]
            },
            "title": "Zeitreihe"
          },
          {
            "name": "Value",
            "type": "number",
            "title": "Value"
          }
        ]
      },
      "title": "Frauen in Führungspositionen in der Wirtschaft sowie im öffentlichen Dienst des Bundes"
    },
    {
      "path": "8-2-c/data.csv",
      "name": "8-2-c",
      "profile": "tabular-data-resource",
      "scheme": "file",
      "format": "csv",
      "hashing": "md5",
      "encoding": "utf-8",
      "schema": {
        "fields": [
          {
            "name": "Year",
            "type": "integer",
            "title": "Jahr"
          },
          {
            "name": "Units",
            "type": "string",
            "constraints": {
              "enum": [
                "Prozent",
                ""
              ]
            },
            "title": "Units"
          },
          {
            "name": "Value",
            "type": "number",
            "title": "Value"
          }
        ]
      },
      "title": "Schuldenstand"
    },
    {
      "path": "6-1-b/data.csv",
      "name": "6-1-b",
      "profile": "tabular-data-resource",
      "scheme": "file",
      "format": "csv",
      "hashing": "md5",
      "encoding": "utf-8",
      "schema": {
        "fields": [
          {
            "name": "Year",
            "type": "integer",
            "title": "Jahr"
          },
          {
            "name": "Units",
            "type": "string",
            "constraints": {
              "enum": [
                "Prozent",
                ""
              ]
            },
            "title": "Units"
          },
          {
            "name": "Value",
            "type": "number",
            "title": "Value"
          }
        ]
      },
      "title": "Nitrat im Grundwasser"
    },
    {
      "path": "1-1-ab/data.csv",
      "name": "1-1-ab",
      "profile": "tabular-data-resource",
      "scheme": "file",
      "format": "csv",
      "hashing": "md5",
      "encoding": "utf-8",
      "schema": {
        "fields": [
          {
            "name": "Year",
            "type": "integer",
            "title": "Jahr"
          },
          {
            "name": "Units",
            "type": "string",
            "constraints": {
              "enum": [
                "Prozent",
                ""
              ]
            },
            "title": "Units"
          },
          {
            "name": "time series",
            "type": "string",
            "constraints": {
              "enum": [
                "a) Materielle und soziale Deprivation",
                "b) Erhebliche materielle und soziale Deprivation",
                ""
              ]
            },
            "title": "Zeitreihe"
          },
          {
            "name": "area",
            "type": "string",
            "constraints": {
              "enum": [
                "Europäische Union",
                "Deutschland",
                ""
              ]
            },
            "title": "Gebiet"
          },
          {
            "name": "sex",
            "type": "string",
            "constraints": {
              "enum": [
                "Weiblich",
                "Männlich",
                ""
              ]
            },
            "title": "Geschlecht"
          },
          {
            "name": "Value",
            "type": "number",
            "title": "Value"
          }
        ]
      },
      "title": "Materielle und soziale Deprivation sowie erhebliche materielle und soziale Deprivation"
    },
    {
      "path": "12-3-abc/data.csv",
      "name": "12-3-abc",
      "profile": "tabular-data-resource",
      "scheme": "file",
      "format": "csv",
      "hashing": "md5",
      "encoding": "utf-8",
      "schema": {
        "fields": [
          {
            "name": "Year",
            "type": "integer",
            "title": "Jahr"
          },
          {
            "name": "Units",
            "type": "string",
            "constraints": {
              "enum": [
                "Prozent",
                "2015 = 100",
                ""
              ]
            },
            "title": "Units"
          },
          {
            "name": "Series",
            "type": "string",
            "constraints": {
              "enum": [
                "a) Nachhaltigkeit in Vergabeverfahren",
                "b) CO₂-Emissionen je Fahrleistungen der Kraftfahrzeuge",
                "c) Nachhaltige Textilbeschaffung",
                ""
              ]
            },
            "title": "Series"
          },
          {
            "name": "Value",
            "type": "number",
            "title": "Value"
          }
        ]
      },
      "title": "Nachhaltige Beschaffung"
    },
    {
      "path": "11-3-a/data.csv",
      "name": "11-3-a",
      "profile": "tabular-data-resource",
      "scheme": "file",
      "format": "csv",
      "hashing": "md5",
      "encoding": "utf-8",
      "schema": {
        "fields": [
          {
            "name": "Year",
            "type": "integer",
            "title": "Jahr"
          },
          {
            "name": "Units",
            "type": "string",
            "constraints": {
              "enum": [
                "Prozent",
                ""
              ]
            },
            "title": "Units"
          },
          {
            "name": "sex",
            "type": "string",
            "constraints": {
              "enum": [
                "Weiblich",
                "Männlich",
                ""
              ]
            },
            "title": "Geschlecht"
          },
          {
            "name": "Value",
            "type": "number",
            "title": "Value"
          }
        ]
      },
      "title": "Anteil der Personen mit hohen Wohnkosten"
    },
    {
      "path": "6-2-ab/data.csv",
      "name": "6-2-ab",
      "profile": "tabular-data-resource",
      "scheme": "file",
      "format": "csv",
      "hashing": "md5",
      "encoding": "utf-8",
      "schema": {
        "fields": [
          {
            "name": "Year",
            "type": "integer",
            "title": "Jahr"
          },
          {
            "name": "Units",
            "type": "string",
            "constraints": {
              "enum": [
                "Millionen",
                ""
              ]
            },
            "title": "Units"
          },
          {
            "name": "time series",
            "type": "string",
            "constraints": {
              "enum": [
                "Mit einem neuen oder hochwertigeren Zugang zur Trinkwasserversorgung oder Anschluss zur Sanitärversorgung",
                "a) Mit einer neuen oder verbesserten Trinkwasserversorgung",
                "b) Mit einer neuen oder verbesserten Basissanitärversorgung oder Abwasserbehandlung",
                ""
              ]
            },
            "title": "Zeitreihe"
          },
          {
            "name": "Value",
            "type": "number",
            "title": "Value"
          }
        ]
      },
      "title": "Entwicklungszusammenarbeit für Trinkwasser- und Sanitärversorgung"
    },
    {
      "path": "5-1-d/data.csv",
      "name": "5-1-d",
      "profile": "tabular-data-resource",
      "scheme": "file",
      "format": "csv",
      "hashing": "md5",
      "encoding": "utf-8",
      "schema": {
        "fields": [
          {
            "name": "Year",
            "type": "integer",
            "title": "Jahr"
          },
          {
            "name": "Units",
            "type": "string",
            "constraints": {
              "enum": [
                "Prozent",
                ""
              ]
            },
            "title": "Units"
          },
          {
            "name": "Series",
            "type": "string",
            "constraints": {
              "enum": [
                "<u>Zeitreihe des Indikators:</u> Kinder, deren Väter Elterngeld bezogen haben",
                "<u>Zusätzliche Zeitreihe:</u> Männliche Bezieher an allen genommenen Elterngeldmonaten",
                ""
              ]
            },
            "title": "Series"
          },
          {
            "name": "Value",
            "type": "number",
            "title": "Value"
          }
        ]
      },
      "title": "Väterbeteiligung beim Elterngeld"
    }
  ]
}